[{"tweetId": "1259883225155018752", "tweetUrl": "https://twitter.com/PlatformIO_Org/status/1259883225155018752", "author": "PlatformIO", "time": 1589214543, "timeFormatted": "May 11", "text": "You asked. We listened! <img alt=\"\ud83e\udde1\" aria-label=\"Emoji: Orange heart\" class=\"Emoji Emoji--forText\" draggable=\"false\" src=\"https://abs.twimg.com/emoji/v2/72x72/1f9e1.png\" title=\"Orange heart\"/> Meet 1-click <a class=\"twitter-hashtag pretty-link js-nav\" data-query-source=\"hashtag_click\" dir=\"ltr\" href=\"https://twitter.com/hashtag/AVR?src=hash\"><s>#</s><b>AVR</b></a> Simulator without a hassle! Learn how <a class=\"twitter-hashtag pretty-link js-nav\" data-query-source=\"hashtag_click\" dir=\"ltr\" href=\"https://twitter.com/hashtag/Arduino?src=hash\"><s>#</s><b>Arduino</b></a> framework works without any hardware on Windows, Linux, or macOS!<br /><img alt=\"\ud83d\udc49\" aria-label=\"Emoji: Right pointing backhand index\" class=\"Emoji Emoji--forText\" draggable=\"false\" src=\"https://abs.twimg.com/emoji/v2/72x72/1f449.png\" title=\"Right pointing backhand index\"/> <a class=\"twitter-timeline-link\" data-expanded-url=\"https://community.platformio.org/t/atmel-avr-dev-platform-v2-1-0-new-boards-avr-simulator-updated-arduino-cores/13627\" dir=\"ltr\" href=\"https://t.co/NTgsKlU196\" rel=\"nofollow noopener\" target=\"_blank\" title=\"https://community.platformio.org/t/atmel-avr-dev-platform-v2-1-0-new-boards-avr-simulator-updated-arduino-cores/13627\"><span class=\"tco-ellipsis\"></span><span class=\"js-display-url\">community.platformio.org/t/atmel-avr-de</span><span class=\"tco-ellipsis\">&hellip;</span></a><br /><img alt=\"\ud83d\udccc\" aria-label=\"Emoji: Pushpin\" class=\"Emoji Emoji--forText\" draggable=\"false\" src=\"https://abs.twimg.com/emoji/v2/72x72/1f4cc.png\" title=\"Pushpin\"/><a class=\"twitter-hashtag pretty-link js-nav\" data-query-source=\"hashtag_click\" dir=\"ltr\" href=\"https://twitter.com/hashtag/Freedom?src=hash\"><s>#</s><b>Freedom</b></a> <a class=\"twitter-hashtag pretty-link js-nav\" data-query-source=\"hashtag_click\" dir=\"ltr\" href=\"https://twitter.com/hashtag/IDE?src=hash\"><s>#</s><b>IDE</b></a> <a class=\"twitter-hashtag pretty-link js-nav\" data-query-source=\"hashtag_click\" dir=\"ltr\" href=\"https://twitter.com/hashtag/CLI?src=hash\"><s>#</s><b>CLI</b></a> <a class=\"twitter-hashtag pretty-link js-nav\" data-query-source=\"hashtag_click\" dir=\"ltr\" href=\"https://twitter.com/hashtag/IoT?src=hash\"><s>#</s><b>IoT</b></a> <a class=\"twitter-hashtag pretty-link js-nav\" data-query-source=\"hashtag_click\" dir=\"ltr\" href=\"https://twitter.com/hashtag/Embedded?src=hash\"><s>#</s><b>Embedded</b></a> <a class=\"twitter-hashtag pretty-link js-nav\" data-query-source=\"hashtag_click\" dir=\"ltr\" href=\"https://twitter.com/hashtag/Debugging?src=hash\"><s>#</s><b>Debugging</b></a> <a class=\"twitter-hashtag pretty-link js-nav\" data-query-source=\"hashtag_click\" dir=\"ltr\" href=\"https://twitter.com/hashtag/UnitTesting?src=hash\"><s>#</s><b>UnitTesting</b></a> <a class=\"twitter-hashtag pretty-link js-nav\" data-query-source=\"hashtag_click\" dir=\"ltr\" href=\"https://twitter.com/hashtag/CodeAnalysis?src=hash\"><s>#</s><b>CodeAnalysis</b></a> <a class=\"twitter-hashtag pretty-link js-nav\" data-query-source=\"hashtag_click\" dir=\"ltr\" href=\"https://twitter.com/hashtag/FirmwareInspection?src=hash\"><s>#</s><b>FirmwareInspection</b></a>", "entries": {"urls": ["https://community.platformio.org/t/atmel-avr-dev-platform-v2-1-0-new-boards-avr-simulator-updated-arduino-cores/13627"], "photos": ["https://news.platformio.org/tweets/PlatformIO_Org/EXv8b0DXgAA3NzF.jpg"]}, "isPinned": false}, {"tweetId": "1259496085296381953", "tweetUrl": "https://twitter.com/Hacksterio/status/1259496085296381953", "author": "Hackster.io", "time": 1589122241, "timeFormatted": "May 10", "text": "Arduino on a $5 RISC-V board: <a class=\"twitter-timeline-link\" data-expanded-url=\"https://bit.ly/3dARCBp\" dir=\"ltr\" href=\"https://t.co/KCRod58wSD\" rel=\"nofollow noopener\" target=\"_blank\" title=\"https://bit.ly/3dARCBp\"><span class=\"tco-ellipsis\"></span><span class=\"js-display-url\">bit.ly/3dARCBp</span><span class=\"tco-ellipsis\"></span></a>", "entries": {"urls": ["https://bit.ly/3dARCBp"], "photos": ["https://news.platformio.org/tweets/PlatformIO_Org/EXqg09OWoAATggj.jpg"]}, "isPinned": false}, {"tweetId": "1258373413418254337", "tweetUrl": "https://twitter.com/PlatformIO_Org/status/1258373413418254337", "author": "PlatformIO", "time": 1588854575, "timeFormatted": "May 7", "text": "Would you like to learn more about RISC-V? Check this RISC-V Assembly Tutorial by Martin Fink from <a class=\"twitter-atreply pretty-link js-nav\" data-mentioned-user-id=\"827296225955180544\" dir=\"ltr\" href=\"https://twitter.com/westerndigital\"><s>@</s><b>westerndigital</b></a> <img alt=\"\ud83d\udca5\" aria-label=\"Emoji: Collision symbol\" class=\"Emoji Emoji--forText\" draggable=\"false\" src=\"https://abs.twimg.com/emoji/v2/72x72/1f4a5.png\" title=\"Collision symbol\"/><br />The project source code and <a class=\"twitter-hashtag pretty-link js-nav\" data-query-source=\"hashtag_click\" dir=\"ltr\" href=\"https://twitter.com/hashtag/video?src=hash\"><s>#</s><b>video</b></a> guide are included!<br /><img alt=\"\ud83d\udc49\" aria-label=\"Emoji: Right pointing backhand index\" class=\"Emoji Emoji--forText\" draggable=\"false\" src=\"https://abs.twimg.com/emoji/v2/72x72/1f449.png\" title=\"Right pointing backhand index\"/> <a class=\"twitter-timeline-link\" data-expanded-url=\"https://docs.platformio.org/en/latest/tutorials/riscv/riscv_asm_video_tutorial.html\" dir=\"ltr\" href=\"https://t.co/AqFtiTCBLz\" rel=\"nofollow noopener\" target=\"_blank\" title=\"https://docs.platformio.org/en/latest/tutorials/riscv/riscv_asm_video_tutorial.html\"><span class=\"tco-ellipsis\"></span><span class=\"js-display-url\">docs.platformio.org/en/latest/tuto</span><span class=\"tco-ellipsis\">&hellip;</span></a><br /><img alt=\"\ud83d\udccc\" aria-label=\"Emoji: Pushpin\" class=\"Emoji Emoji--forText\" draggable=\"false\" src=\"https://abs.twimg.com/emoji/v2/72x72/1f4cc.png\" title=\"Pushpin\"/> <a class=\"twitter-hashtag pretty-link js-nav\" data-query-source=\"hashtag_click\" dir=\"ltr\" href=\"https://twitter.com/hashtag/Tutorial?src=hash\"><s>#</s><b>Tutorial</b></a> <a class=\"twitter-hashtag pretty-link js-nav\" data-query-source=\"hashtag_click\" dir=\"ltr\" href=\"https://twitter.com/hashtag/Assembly?src=hash\"><s>#</s><b>Assembly</b></a> <a class=\"twitter-hashtag pretty-link js-nav\" data-query-source=\"hashtag_click\" dir=\"ltr\" href=\"https://twitter.com/hashtag/Debugging?src=hash\"><s>#</s><b>Debugging</b></a> <a class=\"twitter-hashtag pretty-link js-nav\" data-query-source=\"hashtag_click\" dir=\"ltr\" href=\"https://twitter.com/hashtag/Emulation?src=hash\"><s>#</s><b>Emulation</b></a> <a class=\"twitter-hashtag pretty-link js-nav\" data-query-source=\"hashtag_click\" dir=\"ltr\" href=\"https://twitter.com/hashtag/RISCV?src=hash\"><s>#</s><b>RISCV</b></a> <a class=\"twitter-hashtag pretty-link js-nav\" data-query-source=\"hashtag_click\" dir=\"ltr\" href=\"https://twitter.com/hashtag/OpenSource?src=hash\"><s>#</s><b>OpenSource</b></a>", "entries": {"urls": ["https://docs.platformio.org/en/latest/tutorials/riscv/riscv_asm_video_tutorial.html"], "photos": ["https://news.platformio.org/tweets/PlatformIO_Org/EXagWrhXYAIIecn.jpg"]}, "isPinned": false}, {"tweetId": "1258005178898399232", "tweetUrl": "https://twitter.com/ikravets/status/1258005178898399232", "author": "Ivan Kravets", "time": 1588766781, "timeFormatted": "May 6", "text": "Which Came First, the Chicken or the Egg? <img alt=\"\ud83d\udc14\" aria-label=\"Emoji: Chicken\" class=\"Emoji Emoji--forText\" draggable=\"false\" src=\"https://abs.twimg.com/emoji/v2/72x72/1f414.png\" title=\"Chicken\"/><img alt=\"\ud83e\udd5a\" aria-label=\"Emoji: Egg\" class=\"Emoji Emoji--forText\" draggable=\"false\" src=\"https://abs.twimg.com/emoji/v2/72x72/1f95a.png\" title=\"Egg\"/> <a class=\"twitter-timeline-link\" data-expanded-url=\"https://twitter.com/mbanzi/status/1257980326808338434\" dir=\"ltr\" href=\"https://t.co/7ocs1d8ljr\" rel=\"nofollow noopener\" target=\"_blank\" title=\"https://twitter.com/mbanzi/status/1257980326808338434\"><span class=\"tco-ellipsis\"></span><span class=\"js-display-url\">twitter.com/mbanzi/status/</span><span class=\"tco-ellipsis\">&hellip;</span></a>", "entries": {"urls": ["https://twitter.com/mbanzi/status/1257980326808338434"], "photos": ["https://news.platformio.org/tweets/PlatformIO_Org/EXVUvPeUMAAROtw.jpg"]}, "isPinned": false}, {"tweetId": "1257293781579284483", "tweetUrl": "https://twitter.com/PlatformIO_Org/status/1257293781579284483", "author": "PlatformIO", "time": 1588597171, "timeFormatted": "May 4", "text": "Espressif 8266 dev-platform v2.5.0 is out! <img alt=\"\ud83d\ude80\" aria-label=\"Emoji: Rocket\" class=\"Emoji Emoji--forText\" draggable=\"false\" src=\"https://abs.twimg.com/emoji/v2/72x72/1f680.png\" title=\"Rocket\"/><br />New boards, Arduino core 2.7.0, updated Xtensa toolchain, other improvements<br /><img alt=\"\ud83d\udc49\" aria-label=\"Emoji: Right pointing backhand index\" class=\"Emoji Emoji--forText\" draggable=\"false\" src=\"https://abs.twimg.com/emoji/v2/72x72/1f449.png\" title=\"Right pointing backhand index\"/> <a class=\"twitter-timeline-link\" data-expanded-url=\"https://community.platformio.org/t/espressif-8266-development-platform-2-5-0/13479\" dir=\"ltr\" href=\"https://t.co/WP8aNUomP8\" rel=\"nofollow noopener\" target=\"_blank\" title=\"https://community.platformio.org/t/espressif-8266-development-platform-2-5-0/13479\"><span class=\"tco-ellipsis\"></span><span class=\"js-display-url\">community.platformio.org/t/espressif-82</span><span class=\"tco-ellipsis\">&hellip;</span></a><br /><img alt=\"\ud83d\udccc\" aria-label=\"Emoji: Pushpin\" class=\"Emoji Emoji--forText\" draggable=\"false\" src=\"https://abs.twimg.com/emoji/v2/72x72/1f4cc.png\" title=\"Pushpin\"/> <a class=\"twitter-hashtag pretty-link js-nav\" data-query-source=\"hashtag_click\" dir=\"ltr\" href=\"https://twitter.com/hashtag/Freedom?src=hash\"><s>#</s><b>Freedom</b></a> <a class=\"twitter-hashtag pretty-link js-nav\" data-query-source=\"hashtag_click\" dir=\"ltr\" href=\"https://twitter.com/hashtag/IDE?src=hash\"><s>#</s><b>IDE</b></a> <a class=\"twitter-hashtag pretty-link js-nav\" data-query-source=\"hashtag_click\" dir=\"ltr\" href=\"https://twitter.com/hashtag/CLI?src=hash\"><s>#</s><b>CLI</b></a> <a class=\"twitter-hashtag pretty-link js-nav\" data-query-source=\"hashtag_click\" dir=\"ltr\" href=\"https://twitter.com/hashtag/IoT?src=hash\"><s>#</s><b>IoT</b></a> <a class=\"twitter-hashtag pretty-link js-nav\" data-query-source=\"hashtag_click\" dir=\"ltr\" href=\"https://twitter.com/hashtag/Embedded?src=hash\"><s>#</s><b>Embedded</b></a> <a class=\"twitter-hashtag pretty-link js-nav\" data-query-source=\"hashtag_click\" dir=\"ltr\" href=\"https://twitter.com/hashtag/UnitTesting?src=hash\"><s>#</s><b>UnitTesting</b></a> <a class=\"twitter-hashtag pretty-link js-nav\" data-query-source=\"hashtag_click\" dir=\"ltr\" href=\"https://twitter.com/hashtag/CodeAnalysis?src=hash\"><s>#</s><b>CodeAnalysis</b></a> <a class=\"twitter-hashtag pretty-link js-nav\" data-query-source=\"hashtag_click\" dir=\"ltr\" href=\"https://twitter.com/hashtag/FirmwareInspection?src=hash\"><s>#</s><b>FirmwareInspection</b></a> <a class=\"twitter-hashtag pretty-link js-nav\" data-query-source=\"hashtag_click\" dir=\"ltr\" href=\"https://twitter.com/hashtag/ESP8266?src=hash\"><s>#</s><b>ESP8266</b></a>", "entries": {"urls": ["https://community.platformio.org/t/espressif-8266-development-platform-2-5-0/13479"], "photos": ["https://news.platformio.org/tweets/PlatformIO_Org/EXLM_wSWsAAi-Dl.png"]}, "isPinned": false}, {"tweetId": "1256208886622760962", "tweetUrl": "https://twitter.com/PlatformIO_Org/status/1256208886622760962", "author": "PlatformIO", "time": 1588338512, "timeFormatted": "May 1", "text": "ESP WiFi Timeserver Synchronized <img alt=\"\u231a\ufe0f\" aria-label=\"Emoji: Wristwatch\" class=\"Emoji Emoji--forText\" draggable=\"false\" src=\"https://abs.twimg.com/emoji/v2/72x72/231a.png\" title=\"Wristwatch\"/> Wrist Watch, a great project by Hans-G&uuml;nther Nusseck! Source code and video review are included! <br /><img alt=\"\ud83d\udc49\" aria-label=\"Emoji: Right pointing backhand index\" class=\"Emoji Emoji--forText\" draggable=\"false\" src=\"https://abs.twimg.com/emoji/v2/72x72/1f449.png\" title=\"Right pointing backhand index\"/> <a class=\"twitter-timeline-link\" data-expanded-url=\"https://www.hackster.io/hague/esp-wifi-timeserver-synchronized-wrist-watch-8940cd\" dir=\"ltr\" href=\"https://t.co/mCT5vEnQdV\" rel=\"nofollow noopener\" target=\"_blank\" title=\"https://www.hackster.io/hague/esp-wifi-timeserver-synchronized-wrist-watch-8940cd\"><span class=\"tco-ellipsis\"></span><span class=\"js-display-url\">hackster.io/hague/esp-wifi</span><span class=\"tco-ellipsis\">&hellip;</span></a><br /><img alt=\"\ud83d\udccc\" aria-label=\"Emoji: Pushpin\" class=\"Emoji Emoji--forText\" draggable=\"false\" src=\"https://abs.twimg.com/emoji/v2/72x72/1f4cc.png\" title=\"Pushpin\"/> <a class=\"twitter-hashtag pretty-link js-nav\" data-query-source=\"hashtag_click\" dir=\"ltr\" href=\"https://twitter.com/hashtag/Freedom?src=hash\"><s>#</s><b>Freedom</b></a> <a class=\"twitter-hashtag pretty-link js-nav\" data-query-source=\"hashtag_click\" dir=\"ltr\" href=\"https://twitter.com/hashtag/IDE?src=hash\"><s>#</s><b>IDE</b></a> <a class=\"twitter-hashtag pretty-link js-nav\" data-query-source=\"hashtag_click\" dir=\"ltr\" href=\"https://twitter.com/hashtag/CLI?src=hash\"><s>#</s><b>CLI</b></a> <a class=\"twitter-hashtag pretty-link js-nav\" data-query-source=\"hashtag_click\" dir=\"ltr\" href=\"https://twitter.com/hashtag/IoT?src=hash\"><s>#</s><b>IoT</b></a> <a class=\"twitter-hashtag pretty-link js-nav\" data-query-source=\"hashtag_click\" dir=\"ltr\" href=\"https://twitter.com/hashtag/Embedded?src=hash\"><s>#</s><b>Embedded</b></a> <a class=\"twitter-hashtag pretty-link js-nav\" data-query-source=\"hashtag_click\" dir=\"ltr\" href=\"https://twitter.com/hashtag/UnitTesting?src=hash\"><s>#</s><b>UnitTesting</b></a> <a class=\"twitter-hashtag pretty-link js-nav\" data-query-source=\"hashtag_click\" dir=\"ltr\" href=\"https://twitter.com/hashtag/CodeAnalysis?src=hash\"><s>#</s><b>CodeAnalysis</b></a> <a class=\"twitter-hashtag pretty-link js-nav\" data-query-source=\"hashtag_click\" dir=\"ltr\" href=\"https://twitter.com/hashtag/FirmwareInspection?src=hash\"><s>#</s><b>FirmwareInspection</b></a> <a class=\"twitter-hashtag pretty-link js-nav\" data-query-source=\"hashtag_click\" dir=\"ltr\" href=\"https://twitter.com/hashtag/ESP8266?src=hash\"><s>#</s><b>ESP8266</b></a>", "entries": {"urls": ["https://www.hackster.io/hague/esp-wifi-timeserver-synchronized-wrist-watch-8940cd"], "photos": ["https://news.platformio.org/tweets/PlatformIO_Org/EW7t8DKXsAM2-RW.jpg"]}, "isPinned": false}, {"tweetId": "1255135215552352260", "tweetUrl": "https://twitter.com/PlatformIO_Org/status/1255135215552352260", "author": "PlatformIO", "time": 1588082529, "timeFormatted": "Apr 28", "text": "A new milestone is reached! We support over 800 unique boards and dev-kits! From 8bit to 32bit MCUs, from AVR to Arm and RISC-V architectures! <img alt=\"\ud83c\udf89\" aria-label=\"Emoji: Party popper\" class=\"Emoji Emoji--forText\" draggable=\"false\" src=\"https://abs.twimg.com/emoji/v2/72x72/1f389.png\" title=\"Party popper\"/><br /><img alt=\"\ud83d\udc49\" aria-label=\"Emoji: Right pointing backhand index\" class=\"Emoji Emoji--forText\" draggable=\"false\" src=\"https://abs.twimg.com/emoji/v2/72x72/1f449.png\" title=\"Right pointing backhand index\"/> <a class=\"twitter-timeline-link\" data-expanded-url=\"https://platformio.org/boards\" dir=\"ltr\" href=\"https://t.co/nvuXm8S7Bj\" rel=\"nofollow noopener\" target=\"_blank\" title=\"https://platformio.org/boards\"><span class=\"tco-ellipsis\"></span><span class=\"js-display-url\">platformio.org/boards</span><span class=\"tco-ellipsis\"></span></a><br /><img alt=\"\ud83d\udccc\" aria-label=\"Emoji: Pushpin\" class=\"Emoji Emoji--forText\" draggable=\"false\" src=\"https://abs.twimg.com/emoji/v2/72x72/1f4cc.png\" title=\"Pushpin\"/> <a class=\"twitter-hashtag pretty-link js-nav\" data-query-source=\"hashtag_click\" dir=\"ltr\" href=\"https://twitter.com/hashtag/Freedom?src=hash\"><s>#</s><b>Freedom</b></a> <a class=\"twitter-hashtag pretty-link js-nav\" data-query-source=\"hashtag_click\" dir=\"ltr\" href=\"https://twitter.com/hashtag/IDE?src=hash\"><s>#</s><b>IDE</b></a> <a class=\"twitter-hashtag pretty-link js-nav\" data-query-source=\"hashtag_click\" dir=\"ltr\" href=\"https://twitter.com/hashtag/CLI?src=hash\"><s>#</s><b>CLI</b></a> <a class=\"twitter-hashtag pretty-link js-nav\" data-query-source=\"hashtag_click\" dir=\"ltr\" href=\"https://twitter.com/hashtag/IoT?src=hash\"><s>#</s><b>IoT</b></a> <a class=\"twitter-hashtag pretty-link js-nav\" data-query-source=\"hashtag_click\" dir=\"ltr\" href=\"https://twitter.com/hashtag/Embedded?src=hash\"><s>#</s><b>Embedded</b></a> <a class=\"twitter-hashtag pretty-link js-nav\" data-query-source=\"hashtag_click\" dir=\"ltr\" href=\"https://twitter.com/hashtag/Debugging?src=hash\"><s>#</s><b>Debugging</b></a> <a class=\"twitter-hashtag pretty-link js-nav\" data-query-source=\"hashtag_click\" dir=\"ltr\" href=\"https://twitter.com/hashtag/UnitTesting?src=hash\"><s>#</s><b>UnitTesting</b></a> <a class=\"twitter-hashtag pretty-link js-nav\" data-query-source=\"hashtag_click\" dir=\"ltr\" href=\"https://twitter.com/hashtag/CodeAnalysis?src=hash\"><s>#</s><b>CodeAnalysis</b></a> <a class=\"twitter-hashtag pretty-link js-nav\" data-query-source=\"hashtag_click\" dir=\"ltr\" href=\"https://twitter.com/hashtag/FirmwareInspection?src=hash\"><s>#</s><b>FirmwareInspection</b></a>", "entries": {"urls": ["https://platformio.org/boards"], "photos": ["https://news.platformio.org/tweets/PlatformIO_Org/EWsfBZnU8AA4cKD.jpg"]}, "isPinned": false}, {"tweetId": "1253672289574543361", "tweetUrl": "https://twitter.com/PlatformIO_Org/status/1253672289574543361", "author": "PlatformIO", "time": 1587733740, "timeFormatted": "Apr 24", "text": "An interesting story by Jorge B. Aspiazu on how to work with the STM32 Blue Pill in PlatformIO and not die trying<br /><img alt=\"\ud83d\udc49\" aria-label=\"Emoji: Right pointing backhand index\" class=\"Emoji Emoji--forText\" draggable=\"false\" src=\"https://abs.twimg.com/emoji/v2/72x72/1f449.png\" title=\"Right pointing backhand index\"/> <a class=\"twitter-timeline-link\" data-expanded-url=\"https://medium.com/@jobenas_25464/how-to-work-with-the-stm32-blue-pill-in-platformio-and-not-die-trying-1700250e54e2\" dir=\"ltr\" href=\"https://t.co/DVNEDPHGA4\" rel=\"nofollow noopener\" target=\"_blank\" title=\"https://medium.com/@jobenas_25464/how-to-work-with-the-stm32-blue-pill-in-platformio-and-not-die-trying-1700250e54e2\"><span class=\"tco-ellipsis\"></span><span class=\"js-display-url\">medium.com/@jobenas_25464</span><span class=\"tco-ellipsis\">&hellip;</span></a><br /><img alt=\"\ud83d\udccc\" aria-label=\"Emoji: Pushpin\" class=\"Emoji Emoji--forText\" draggable=\"false\" src=\"https://abs.twimg.com/emoji/v2/72x72/1f4cc.png\" title=\"Pushpin\"/> <a class=\"twitter-hashtag pretty-link js-nav\" data-query-source=\"hashtag_click\" dir=\"ltr\" href=\"https://twitter.com/hashtag/Freedom?src=hash\"><s>#</s><b>Freedom</b></a> <a class=\"twitter-hashtag pretty-link js-nav\" data-query-source=\"hashtag_click\" dir=\"ltr\" href=\"https://twitter.com/hashtag/IDE?src=hash\"><s>#</s><b>IDE</b></a> <a class=\"twitter-hashtag pretty-link js-nav\" data-query-source=\"hashtag_click\" dir=\"ltr\" href=\"https://twitter.com/hashtag/CLI?src=hash\"><s>#</s><b>CLI</b></a> <a class=\"twitter-hashtag pretty-link js-nav\" data-query-source=\"hashtag_click\" dir=\"ltr\" href=\"https://twitter.com/hashtag/IoT?src=hash\"><s>#</s><b>IoT</b></a> <a class=\"twitter-hashtag pretty-link js-nav\" data-query-source=\"hashtag_click\" dir=\"ltr\" href=\"https://twitter.com/hashtag/Embedded?src=hash\"><s>#</s><b>Embedded</b></a> <a class=\"twitter-hashtag pretty-link js-nav\" data-query-source=\"hashtag_click\" dir=\"ltr\" href=\"https://twitter.com/hashtag/Debugging?src=hash\"><s>#</s><b>Debugging</b></a> <a class=\"twitter-hashtag pretty-link js-nav\" data-query-source=\"hashtag_click\" dir=\"ltr\" href=\"https://twitter.com/hashtag/UnitTesting?src=hash\"><s>#</s><b>UnitTesting</b></a> <a class=\"twitter-hashtag pretty-link js-nav\" data-query-source=\"hashtag_click\" dir=\"ltr\" href=\"https://twitter.com/hashtag/CodeAnalysis?src=hash\"><s>#</s><b>CodeAnalysis</b></a> <a class=\"twitter-hashtag pretty-link js-nav\" data-query-source=\"hashtag_click\" dir=\"ltr\" href=\"https://twitter.com/hashtag/FirmwareInspection?src=hash\"><s>#</s><b>FirmwareInspection</b></a>", "entries": {"urls": ["https://medium.com/@jobenas_25464/how-to-work-with-the-stm32-blue-pill-in-platformio-and-not-die-trying-1700250e54e2"], "photos": ["https://news.platformio.org/tweets/PlatformIO_Org/EWXvaYIXYAAIsX2.jpg"]}, "isPinned": false}, {"tweetId": "1252222403318624256", "tweetUrl": "https://twitter.com/PlatformIO_Org/status/1252222403318624256", "author": "PlatformIO", "time": 1587388060, "timeFormatted": "Apr 20", "text": "Special for you! <img alt=\"\ud83e\udde1\" aria-label=\"Emoji: Orange heart\" class=\"Emoji Emoji--forText\" draggable=\"false\" src=\"https://abs.twimg.com/emoji/v2/72x72/1f9e1.png\" title=\"Orange heart\"/> An official step-by-step guide for ESP-IDF without pain, dependencies, and complexity! <img alt=\"\ud83d\ude91\" aria-label=\"Emoji: Ambulance\" class=\"Emoji Emoji--forText\" draggable=\"false\" src=\"https://abs.twimg.com/emoji/v2/72x72/1f691.png\" title=\"Ambulance\"/> Just 1-click!<br /><img alt=\"\u2705\" aria-label=\"Emoji: White heavy check mark\" class=\"Emoji Emoji--forText\" draggable=\"false\" src=\"https://abs.twimg.com/emoji/v2/72x72/2705.png\" title=\"White heavy check mark\"/> Debugging<br /><img alt=\"\u2705\" aria-label=\"Emoji: White heavy check mark\" class=\"Emoji Emoji--forText\" draggable=\"false\" src=\"https://abs.twimg.com/emoji/v2/72x72/2705.png\" title=\"White heavy check mark\"/> Unit Testing<br /><img alt=\"\u2705\" aria-label=\"Emoji: White heavy check mark\" class=\"Emoji Emoji--forText\" draggable=\"false\" src=\"https://abs.twimg.com/emoji/v2/72x72/2705.png\" title=\"White heavy check mark\"/> Code Analysis<br /><img alt=\"\u2705\" aria-label=\"Emoji: White heavy check mark\" class=\"Emoji Emoji--forText\" draggable=\"false\" src=\"https://abs.twimg.com/emoji/v2/72x72/2705.png\" title=\"White heavy check mark\"/> Firmware Inspection<br /><img alt=\"\ud83d\udc49\" aria-label=\"Emoji: Right pointing backhand index\" class=\"Emoji Emoji--forText\" draggable=\"false\" src=\"https://abs.twimg.com/emoji/v2/72x72/1f449.png\" title=\"Right pointing backhand index\"/> <a class=\"twitter-timeline-link\" data-expanded-url=\"https://docs.platformio.org/en/latest/tutorials/espressif32/espidf_debugging_unit_testing_analysis.html\" dir=\"ltr\" href=\"https://t.co/0xVq5ckVEd\" rel=\"nofollow noopener\" target=\"_blank\" title=\"https://docs.platformio.org/en/latest/tutorials/espressif32/espidf_debugging_unit_testing_analysis.html\"><span class=\"tco-ellipsis\"></span><span class=\"js-display-url\">docs.platformio.org/en/latest/tuto</span><span class=\"tco-ellipsis\">&hellip;</span></a><br /><img alt=\"\ud83d\udccc\" aria-label=\"Emoji: Pushpin\" class=\"Emoji Emoji--forText\" draggable=\"false\" src=\"https://abs.twimg.com/emoji/v2/72x72/1f4cc.png\" title=\"Pushpin\"/> <a class=\"twitter-hashtag pretty-link js-nav\" data-query-source=\"hashtag_click\" dir=\"ltr\" href=\"https://twitter.com/hashtag/Freedom?src=hash\"><s>#</s><b>Freedom</b></a> <a class=\"twitter-hashtag pretty-link js-nav\" data-query-source=\"hashtag_click\" dir=\"ltr\" href=\"https://twitter.com/hashtag/IDE?src=hash\"><s>#</s><b>IDE</b></a> <a class=\"twitter-hashtag pretty-link js-nav\" data-query-source=\"hashtag_click\" dir=\"ltr\" href=\"https://twitter.com/hashtag/CLI?src=hash\"><s>#</s><b>CLI</b></a> <a class=\"twitter-hashtag pretty-link js-nav\" data-query-source=\"hashtag_click\" dir=\"ltr\" href=\"https://twitter.com/hashtag/IoT?src=hash\"><s>#</s><b>IoT</b></a> <a class=\"twitter-hashtag pretty-link js-nav\" data-query-source=\"hashtag_click\" dir=\"ltr\" href=\"https://twitter.com/hashtag/Embedded?src=hash\"><s>#</s><b>Embedded</b></a> <a class=\"twitter-hashtag pretty-link js-nav\" data-query-source=\"hashtag_click\" dir=\"ltr\" href=\"https://twitter.com/hashtag/ESP32?src=hash\"><s>#</s><b>ESP32</b></a>", "entries": {"urls": ["https://docs.platformio.org/en/latest/tutorials/espressif32/espidf_debugging_unit_testing_analysis.html"], "photos": ["https://news.platformio.org/tweets/PlatformIO_Org/EWDHyKsWsAA9wc3.png", "https://news.platformio.org/tweets/PlatformIO_Org/EWDHytyXkAcI8WC.png", "https://news.platformio.org/tweets/PlatformIO_Org/EWDH0ykWsAAIJ95.jpg"]}, "isPinned": false}, {"tweetId": "1251141613759238146", "tweetUrl": "https://twitter.com/PlatformIO_Org/status/1251141613759238146", "author": "PlatformIO", "time": 1587130380, "timeFormatted": "Apr 17", "text": "Just one month and we've reached <img alt=\"\ud83c\udf1f\" aria-label=\"Emoji: Glowing star\" class=\"Emoji Emoji--forText\" draggable=\"false\" src=\"https://abs.twimg.com/emoji/v2/72x72/1f31f.png\" title=\"Glowing star\"/> 900 Five-Star reviews <img alt=\"\ud83c\udf1f\" aria-label=\"Emoji: Glowing star\" class=\"Emoji Emoji--forText\" draggable=\"false\" src=\"https://abs.twimg.com/emoji/v2/72x72/1f31f.png\" title=\"Glowing star\"/> and 800,000 unique installations for <a class=\"twitter-hashtag pretty-link js-nav\" data-query-source=\"hashtag_click\" dir=\"ltr\" href=\"https://twitter.com/hashtag/PlatformIO?src=hash\"><s>#</s><b>PlatformIO</b></a> extension for <a class=\"twitter-hashtag pretty-link js-nav\" data-query-source=\"hashtag_click\" dir=\"ltr\" href=\"https://twitter.com/hashtag/VSCode?src=hash\"><s>#</s><b>VSCode</b></a>!<br />Thank you so much for your feedback! <img alt=\"\ud83e\udde1\" aria-label=\"Emoji: Orange heart\" class=\"Emoji Emoji--forText\" draggable=\"false\" src=\"https://abs.twimg.com/emoji/v2/72x72/1f9e1.png\" title=\"Orange heart\"/><br /><img alt=\"\ud83d\udc49\" aria-label=\"Emoji: Right pointing backhand index\" class=\"Emoji Emoji--forText\" draggable=\"false\" src=\"https://abs.twimg.com/emoji/v2/72x72/1f449.png\" title=\"Right pointing backhand index\"/> <a class=\"twitter-timeline-link\" data-expanded-url=\"https://marketplace.visualstudio.com/items?itemName=platformio.platformio-ide\" dir=\"ltr\" href=\"https://t.co/A2uMrwQFtU\" rel=\"nofollow noopener\" target=\"_blank\" title=\"https://marketplace.visualstudio.com/items?itemName=platformio.platformio-ide\"><span class=\"tco-ellipsis\"></span><span class=\"js-display-url\">marketplace.visualstudio.com/items?itemName</span><span class=\"tco-ellipsis\">&hellip;</span></a><br /><img alt=\"\ud83d\udccc\" aria-label=\"Emoji: Pushpin\" class=\"Emoji Emoji--forText\" draggable=\"false\" src=\"https://abs.twimg.com/emoji/v2/72x72/1f4cc.png\" title=\"Pushpin\"/> <a class=\"twitter-hashtag pretty-link js-nav\" data-query-source=\"hashtag_click\" dir=\"ltr\" href=\"https://twitter.com/hashtag/Freedom?src=hash\"><s>#</s><b>Freedom</b></a> <a class=\"twitter-hashtag pretty-link js-nav\" data-query-source=\"hashtag_click\" dir=\"ltr\" href=\"https://twitter.com/hashtag/Embedded?src=hash\"><s>#</s><b>Embedded</b></a> <a class=\"twitter-hashtag pretty-link js-nav\" data-query-source=\"hashtag_click\" dir=\"ltr\" href=\"https://twitter.com/hashtag/OpenSource?src=hash\"><s>#</s><b>OpenSource</b></a> <a class=\"twitter-hashtag pretty-link js-nav\" data-query-source=\"hashtag_click\" dir=\"ltr\" href=\"https://twitter.com/hashtag/IDE?src=hash\"><s>#</s><b>IDE</b></a> <a class=\"twitter-hashtag pretty-link js-nav\" data-query-source=\"hashtag_click\" dir=\"ltr\" href=\"https://twitter.com/hashtag/Debugging?src=hash\"><s>#</s><b>Debugging</b></a> <a class=\"twitter-hashtag pretty-link js-nav\" data-query-source=\"hashtag_click\" dir=\"ltr\" href=\"https://twitter.com/hashtag/UnitTesting?src=hash\"><s>#</s><b>UnitTesting</b></a> <a class=\"twitter-hashtag pretty-link js-nav\" data-query-source=\"hashtag_click\" dir=\"ltr\" href=\"https://twitter.com/hashtag/CodeInspection?src=hash\"><s>#</s><b>CodeInspection</b></a>", "entries": {"urls": ["https://marketplace.visualstudio.com/items?itemName=platformio.platformio-ide"], "photos": ["https://news.platformio.org/tweets/PlatformIO_Org/EVzv82mWAAArfRT.jpg"]}, "isPinned": false}, {"tweetId": "1250878859672793095", "tweetUrl": "https://twitter.com/clion_ide/status/1250878859672793095", "author": "JetBrains CLion IDE", "time": 1587067735, "timeFormatted": "Apr 16", "text": "We keep improving CLion for embedded development. v2020.1 brings IAR compiler support and a plugin for <a class=\"twitter-atreply pretty-link js-nav\" data-mentioned-user-id=\"2848528606\" dir=\"ltr\" href=\"https://twitter.com/PlatformIO_Org\"><s>@</s><b>PlatformIO_Org</b></a> <a class=\"twitter-timeline-link\" data-expanded-url=\"https://blog.jetbrains.com/clion/2020/04/clion-2020-1-cuda-clang-embedded/#embedded_development\" dir=\"ltr\" href=\"https://t.co/Cya7jUrBLw\" rel=\"nofollow noopener\" target=\"_blank\" title=\"https://blog.jetbrains.com/clion/2020/04/clion-2020-1-cuda-clang-embedded/#embedded_development\"><span class=\"tco-ellipsis\"></span><span class=\"js-display-url\">blog.jetbrains.com/clion/2020/04/</span><span class=\"tco-ellipsis\">&hellip;</span></a>", "entries": {"urls": ["https://blog.jetbrains.com/clion/2020/04/clion-2020-1-cuda-clang-embedded/#embedded_development"], "photos": ["https://news.platformio.org/tweets/PlatformIO_Org/wBTzM4-h_bigger.jpg"]}, "isPinned": false}, {"tweetId": "1250353959081934856", "tweetUrl": "https://twitter.com/PlatformIO_Org/status/1250353959081934856", "author": "PlatformIO", "time": 1586942588, "timeFormatted": "Apr 15", "text": "It's a big honor for <a class=\"twitter-hashtag pretty-link js-nav\" data-query-source=\"hashtag_click\" dir=\"ltr\" href=\"https://twitter.com/hashtag/PlatformIO?src=hash\"><s>#</s><b>PlatformIO</b></a> to be a part of this massive update for <a class=\"twitter-atreply pretty-link js-nav\" data-mentioned-user-id=\"2668989936\" dir=\"ltr\" href=\"https://twitter.com/clion_ide\"><s>@</s><b>clion_ide</b></a>! Thanks, JetBrains Team, for the official plugin for PlatformIO!<br /><img alt=\"\ud83d\udc49\" aria-label=\"Emoji: Right pointing backhand index\" class=\"Emoji Emoji--forText\" draggable=\"false\" src=\"https://abs.twimg.com/emoji/v2/72x72/1f449.png\" title=\"Right pointing backhand index\"/> <a class=\"twitter-timeline-link\" data-expanded-url=\"https://www.jetbrains.com/clion/whatsnew/\" dir=\"ltr\" href=\"https://t.co/yCNtVKWUTl\" rel=\"nofollow noopener\" target=\"_blank\" title=\"https://www.jetbrains.com/clion/whatsnew/\"><span class=\"tco-ellipsis\"></span><span class=\"js-display-url\">jetbrains.com/clion/whatsnew/</span><span class=\"tco-ellipsis\"></span></a><br /><img alt=\"\ud83d\udccc\" aria-label=\"Emoji: Pushpin\" class=\"Emoji Emoji--forText\" draggable=\"false\" src=\"https://abs.twimg.com/emoji/v2/72x72/1f4cc.png\" title=\"Pushpin\"/> <a class=\"twitter-hashtag pretty-link js-nav\" data-query-source=\"hashtag_click\" dir=\"ltr\" href=\"https://twitter.com/hashtag/Freedom?src=hash\"><s>#</s><b>Freedom</b></a> <a class=\"twitter-hashtag pretty-link js-nav\" data-query-source=\"hashtag_click\" dir=\"ltr\" href=\"https://twitter.com/hashtag/IDE?src=hash\"><s>#</s><b>IDE</b></a> <a class=\"twitter-hashtag pretty-link js-nav\" data-query-source=\"hashtag_click\" dir=\"ltr\" href=\"https://twitter.com/hashtag/CLI?src=hash\"><s>#</s><b>CLI</b></a> <a class=\"twitter-hashtag pretty-link js-nav\" data-query-source=\"hashtag_click\" dir=\"ltr\" href=\"https://twitter.com/hashtag/IoT?src=hash\"><s>#</s><b>IoT</b></a> <a class=\"twitter-hashtag pretty-link js-nav\" data-query-source=\"hashtag_click\" dir=\"ltr\" href=\"https://twitter.com/hashtag/Embedded?src=hash\"><s>#</s><b>Embedded</b></a> <a class=\"twitter-hashtag pretty-link js-nav\" data-query-source=\"hashtag_click\" dir=\"ltr\" href=\"https://twitter.com/hashtag/Debugging?src=hash\"><s>#</s><b>Debugging</b></a> <a class=\"twitter-hashtag pretty-link js-nav\" data-query-source=\"hashtag_click\" dir=\"ltr\" href=\"https://twitter.com/hashtag/UnitTesting?src=hash\"><s>#</s><b>UnitTesting</b></a> <a class=\"twitter-hashtag pretty-link js-nav\" data-query-source=\"hashtag_click\" dir=\"ltr\" href=\"https://twitter.com/hashtag/CodeAnalysis?src=hash\"><s>#</s><b>CodeAnalysis</b></a> <a class=\"twitter-hashtag pretty-link js-nav\" data-query-source=\"hashtag_click\" dir=\"ltr\" href=\"https://twitter.com/hashtag/FirmwareInspection?src=hash\"><s>#</s><b>FirmwareInspection</b></a>", "entries": {"urls": ["https://www.jetbrains.com/clion/whatsnew/"], "photos": ["https://news.platformio.org/tweets/PlatformIO_Org/EVkwaIvWsAABIp8.png"]}, "isPinned": false}, {"tweetId": "1249181634815016961", "tweetUrl": "https://twitter.com/alvaroviebrantz/status/1249181634815016961", "author": "Alvaro Viebrantz", "time": 1586663085, "timeFormatted": "Apr 11", "text": "Playing with <a class=\"twitter-atreply pretty-link js-nav\" data-mentioned-user-id=\"455210426\" dir=\"ltr\" href=\"https://twitter.com/NordicTweets\"><s>@</s><b>NordicTweets</b></a> nrf52840, running <a class=\"twitter-atreply pretty-link js-nav\" data-mentioned-user-id=\"4889353644\" dir=\"ltr\" href=\"https://twitter.com/ZephyrIoT\"><s>@</s><b>ZephyrIoT</b></a> with <a class=\"twitter-atreply pretty-link js-nav\" data-mentioned-user-id=\"2848528606\" dir=\"ltr\" href=\"https://twitter.com/PlatformIO_Org\"><s>@</s><b>PlatformIO_Org</b></a> support for it. Device provides an BLE uart interface that accepts the commands. App was built with <a class=\"twitter-atreply pretty-link js-nav\" data-mentioned-user-id=\"420730316\" dir=\"ltr\" href=\"https://twitter.com/FlutterDev\"><s>@</s><b>FlutterDev</b></a>. Code is pretty ugly right now, but if you're interested <a class=\"twitter-timeline-link\" data-expanded-url=\"http://github.com/alvarowolfx/ble-rgb-light-flutter\" dir=\"ltr\" href=\"https://t.co/58zgOjONoN\" rel=\"nofollow noopener\" target=\"_blank\" title=\"http://github.com/alvarowolfx/ble-rgb-light-flutter\"><span class=\"tco-ellipsis\"></span><span class=\"js-display-url\">github.com/alvarowolfx/bl</span><span class=\"tco-ellipsis\">&hellip;</span></a> <a class=\"twitter-hashtag pretty-link js-nav\" data-query-source=\"hashtag_click\" dir=\"ltr\" href=\"https://twitter.com/hashtag/gde?src=hash\"><s>#</s><b>gde</b></a> <a class=\"twitter-hashtag pretty-link js-nav\" data-query-source=\"hashtag_click\" dir=\"ltr\" href=\"https://twitter.com/hashtag/iot?src=hash\"><s>#</s><b>iot</b></a>", "entries": {"urls": ["http://github.com/alvarowolfx/ble-rgb-light-flutter"], "photos": ["https://news.platformio.org/tweets/PlatformIO_Org/TtrgG-9I_bigger.jpg"]}, "isPinned": false}, {"tweetId": "1248567226376032256", "tweetUrl": "https://twitter.com/PlatformIO_Org/status/1248567226376032256", "author": "PlatformIO", "time": 1586516598, "timeFormatted": "Apr 10", "text": "At your request &ndash; initial support for NXP <a class=\"twitter-timeline-link\" data-expanded-url=\"http://i.MX\" dir=\"ltr\" href=\"https://t.co/cb78nx85sn\" rel=\"nofollow noopener\" target=\"_blank\" title=\"http://i.MX\"><span class=\"tco-ellipsis\"></span><span class=\"js-display-url\">i.MX</span><span class=\"tco-ellipsis\"></span></a> RT dev-platform <img alt=\"\ud83d\ude80\" aria-label=\"Emoji: Rocket\" class=\"Emoji Emoji--forText\" draggable=\"false\" src=\"https://abs.twimg.com/emoji/v2/72x72/1f680.png\" title=\"Rocket\"/><br />New boards, <a class=\"twitter-hashtag pretty-link js-nav\" data-query-source=\"hashtag_click\" dir=\"ltr\" href=\"https://twitter.com/hashtag/Zephyr?src=hash\"><s>#</s><b>Zephyr</b></a> <a class=\"twitter-hashtag pretty-link js-nav\" data-query-source=\"hashtag_click\" dir=\"ltr\" href=\"https://twitter.com/hashtag/RTOS?src=hash\"><s>#</s><b>RTOS</b></a> and <a class=\"twitter-hashtag pretty-link js-nav\" data-query-source=\"hashtag_click\" dir=\"ltr\" href=\"https://twitter.com/hashtag/Mbed?src=hash\"><s>#</s><b>Mbed</b></a> OS frameworks<br /><img alt=\"\ud83d\udc49\" aria-label=\"Emoji: Right pointing backhand index\" class=\"Emoji Emoji--forText\" draggable=\"false\" src=\"https://abs.twimg.com/emoji/v2/72x72/1f449.png\" title=\"Right pointing backhand index\"/> <a class=\"twitter-timeline-link\" data-expanded-url=\"https://community.platformio.org/t/initial-release-of-nxp-i-mx-rt-development-platform/12991\" dir=\"ltr\" href=\"https://t.co/e3l0ff5Mm3\" rel=\"nofollow noopener\" target=\"_blank\" title=\"https://community.platformio.org/t/initial-release-of-nxp-i-mx-rt-development-platform/12991\"><span class=\"tco-ellipsis\"></span><span class=\"js-display-url\">community.platformio.org/t/initial-rele</span><span class=\"tco-ellipsis\">&hellip;</span></a><br /><img alt=\"\ud83d\udccc\" aria-label=\"Emoji: Pushpin\" class=\"Emoji Emoji--forText\" draggable=\"false\" src=\"https://abs.twimg.com/emoji/v2/72x72/1f4cc.png\" title=\"Pushpin\"/> <a class=\"twitter-hashtag pretty-link js-nav\" data-query-source=\"hashtag_click\" dir=\"ltr\" href=\"https://twitter.com/hashtag/Freedom?src=hash\"><s>#</s><b>Freedom</b></a> <a class=\"twitter-hashtag pretty-link js-nav\" data-query-source=\"hashtag_click\" dir=\"ltr\" href=\"https://twitter.com/hashtag/IDE?src=hash\"><s>#</s><b>IDE</b></a> <a class=\"twitter-hashtag pretty-link js-nav\" data-query-source=\"hashtag_click\" dir=\"ltr\" href=\"https://twitter.com/hashtag/CLI?src=hash\"><s>#</s><b>CLI</b></a> <a class=\"twitter-hashtag pretty-link js-nav\" data-query-source=\"hashtag_click\" dir=\"ltr\" href=\"https://twitter.com/hashtag/IoT?src=hash\"><s>#</s><b>IoT</b></a> <a class=\"twitter-hashtag pretty-link js-nav\" data-query-source=\"hashtag_click\" dir=\"ltr\" href=\"https://twitter.com/hashtag/Embedded?src=hash\"><s>#</s><b>Embedded</b></a> <a class=\"twitter-hashtag pretty-link js-nav\" data-query-source=\"hashtag_click\" dir=\"ltr\" href=\"https://twitter.com/hashtag/Debugging?src=hash\"><s>#</s><b>Debugging</b></a> <a class=\"twitter-hashtag pretty-link js-nav\" data-query-source=\"hashtag_click\" dir=\"ltr\" href=\"https://twitter.com/hashtag/UnitTesting?src=hash\"><s>#</s><b>UnitTesting</b></a> <a class=\"twitter-hashtag pretty-link js-nav\" data-query-source=\"hashtag_click\" dir=\"ltr\" href=\"https://twitter.com/hashtag/CodeAnalysis?src=hash\"><s>#</s><b>CodeAnalysis</b></a> <a class=\"twitter-hashtag pretty-link js-nav\" data-query-source=\"hashtag_click\" dir=\"ltr\" href=\"https://twitter.com/hashtag/FirmwareInspection?src=hash\"><s>#</s><b>FirmwareInspection</b></a>", "entries": {"urls": ["http://i.MX", "https://community.platformio.org/t/initial-release-of-nxp-i-mx-rt-development-platform/12991"], "photos": ["https://news.platformio.org/tweets/PlatformIO_Org/EVPM8zyU4AERZfy.png"]}, "isPinned": false}, {"tweetId": "1247850274183680002", "tweetUrl": "https://twitter.com/PlatformIO_Org/status/1247850274183680002", "author": "PlatformIO", "time": 1586345663, "timeFormatted": "Apr 8", "text": "6 reasons by Tech Explorations why you should use PlatformIO:<br /><img alt=\"\u2705\" aria-label=\"Emoji: White heavy check mark\" class=\"Emoji Emoji--forText\" draggable=\"false\" src=\"https://abs.twimg.com/emoji/v2/72x72/2705.png\" title=\"White heavy check mark\"/> Control of project dependencies<br /><img alt=\"\u2705\" aria-label=\"Emoji: White heavy check mark\" class=\"Emoji Emoji--forText\" draggable=\"false\" src=\"https://abs.twimg.com/emoji/v2/72x72/2705.png\" title=\"White heavy check mark\"/> Projects are self-contained<br /><img alt=\"\u2705\" aria-label=\"Emoji: White heavy check mark\" class=\"Emoji Emoji--forText\" draggable=\"false\" src=\"https://abs.twimg.com/emoji/v2/72x72/2705.png\" title=\"White heavy check mark\"/> Toolchains integration<br /><img alt=\"\ud83d\udc49\" aria-label=\"Emoji: Right pointing backhand index\" class=\"Emoji Emoji--forText\" draggable=\"false\" src=\"https://abs.twimg.com/emoji/v2/72x72/1f449.png\" title=\"Right pointing backhand index\"/> <a class=\"twitter-timeline-link\" data-expanded-url=\"https://techexplorations.com/guides/esp32/unleashed/platformio/\" dir=\"ltr\" href=\"https://t.co/9rcGVeiJEY\" rel=\"nofollow noopener\" target=\"_blank\" title=\"https://techexplorations.com/guides/esp32/unleashed/platformio/\"><span class=\"tco-ellipsis\"></span><span class=\"js-display-url\">techexplorations.com/guides/esp32/u</span><span class=\"tco-ellipsis\">&hellip;</span></a><br /><img alt=\"\ud83d\udccc\" aria-label=\"Emoji: Pushpin\" class=\"Emoji Emoji--forText\" draggable=\"false\" src=\"https://abs.twimg.com/emoji/v2/72x72/1f4cc.png\" title=\"Pushpin\"/> <a class=\"twitter-hashtag pretty-link js-nav\" data-query-source=\"hashtag_click\" dir=\"ltr\" href=\"https://twitter.com/hashtag/Freedom?src=hash\"><s>#</s><b>Freedom</b></a> <a class=\"twitter-hashtag pretty-link js-nav\" data-query-source=\"hashtag_click\" dir=\"ltr\" href=\"https://twitter.com/hashtag/IDE?src=hash\"><s>#</s><b>IDE</b></a> <a class=\"twitter-hashtag pretty-link js-nav\" data-query-source=\"hashtag_click\" dir=\"ltr\" href=\"https://twitter.com/hashtag/CLI?src=hash\"><s>#</s><b>CLI</b></a> <a class=\"twitter-hashtag pretty-link js-nav\" data-query-source=\"hashtag_click\" dir=\"ltr\" href=\"https://twitter.com/hashtag/IoT?src=hash\"><s>#</s><b>IoT</b></a> <a class=\"twitter-hashtag pretty-link js-nav\" data-query-source=\"hashtag_click\" dir=\"ltr\" href=\"https://twitter.com/hashtag/Embedded?src=hash\"><s>#</s><b>Embedded</b></a> <a class=\"twitter-hashtag pretty-link js-nav\" data-query-source=\"hashtag_click\" dir=\"ltr\" href=\"https://twitter.com/hashtag/Debugging?src=hash\"><s>#</s><b>Debugging</b></a> <a class=\"twitter-hashtag pretty-link js-nav\" data-query-source=\"hashtag_click\" dir=\"ltr\" href=\"https://twitter.com/hashtag/UnitTesting?src=hash\"><s>#</s><b>UnitTesting</b></a> <a class=\"twitter-hashtag pretty-link js-nav\" data-query-source=\"hashtag_click\" dir=\"ltr\" href=\"https://twitter.com/hashtag/CodeAnalysis?src=hash\"><s>#</s><b>CodeAnalysis</b></a> <a class=\"twitter-hashtag pretty-link js-nav\" data-query-source=\"hashtag_click\" dir=\"ltr\" href=\"https://twitter.com/hashtag/FirmwareInspection?src=hash\"><s>#</s><b>FirmwareInspection</b></a>", "entries": {"urls": ["https://techexplorations.com/guides/esp32/unleashed/platformio/"], "photos": ["https://news.platformio.org/tweets/PlatformIO_Org/EVE9ll8U0AAJv_P.jpg"]}, "isPinned": false}, {"tweetId": "1247161900833460225", "tweetUrl": "https://twitter.com/PlatformIO_Org/status/1247161900833460225", "author": "PlatformIO", "time": 1586181542, "timeFormatted": "Apr 6", "text": "Huge update for ST STM32 dev-platform! <img alt=\"\ud83c\udf89\" aria-label=\"Emoji: Party popper\" class=\"Emoji Emoji--forText\" draggable=\"false\" src=\"https://abs.twimg.com/emoji/v2/72x72/1f389.png\" title=\"Party popper\"/><br />New boards, <a class=\"twitter-hashtag pretty-link js-nav\" data-query-source=\"hashtag_click\" dir=\"ltr\" href=\"https://twitter.com/hashtag/Zephyr?src=hash\"><s>#</s><b>Zephyr</b></a> <a class=\"twitter-hashtag pretty-link js-nav\" data-query-source=\"hashtag_click\" dir=\"ltr\" href=\"https://twitter.com/hashtag/RTOS?src=hash\"><s>#</s><b>RTOS</b></a> v2.2, <a class=\"twitter-hashtag pretty-link js-nav\" data-query-source=\"hashtag_click\" dir=\"ltr\" href=\"https://twitter.com/hashtag/Arduino?src=hash\"><s>#</s><b>Arduino</b></a> core v1.8, other improvements<br /><img alt=\"\ud83d\udc49\" aria-label=\"Emoji: Right pointing backhand index\" class=\"Emoji Emoji--forText\" draggable=\"false\" src=\"https://abs.twimg.com/emoji/v2/72x72/1f449.png\" title=\"Right pointing backhand index\"/> <a class=\"twitter-timeline-link\" data-expanded-url=\"https://community.platformio.org/t/st-stm32-dev-platform-6-1-0/12905\" dir=\"ltr\" href=\"https://t.co/l64aUiaFVH\" rel=\"nofollow noopener\" target=\"_blank\" title=\"https://community.platformio.org/t/st-stm32-dev-platform-6-1-0/12905\"><span class=\"tco-ellipsis\"></span><span class=\"js-display-url\">community.platformio.org/t/st-stm32-dev</span><span class=\"tco-ellipsis\">&hellip;</span></a><br /><img alt=\"\ud83d\udccc\" aria-label=\"Emoji: Pushpin\" class=\"Emoji Emoji--forText\" draggable=\"false\" src=\"https://abs.twimg.com/emoji/v2/72x72/1f4cc.png\" title=\"Pushpin\"/> <a class=\"twitter-hashtag pretty-link js-nav\" data-query-source=\"hashtag_click\" dir=\"ltr\" href=\"https://twitter.com/hashtag/Freedom?src=hash\"><s>#</s><b>Freedom</b></a> <a class=\"twitter-hashtag pretty-link js-nav\" data-query-source=\"hashtag_click\" dir=\"ltr\" href=\"https://twitter.com/hashtag/IDE?src=hash\"><s>#</s><b>IDE</b></a> <a class=\"twitter-hashtag pretty-link js-nav\" data-query-source=\"hashtag_click\" dir=\"ltr\" href=\"https://twitter.com/hashtag/CLI?src=hash\"><s>#</s><b>CLI</b></a> <a class=\"twitter-hashtag pretty-link js-nav\" data-query-source=\"hashtag_click\" dir=\"ltr\" href=\"https://twitter.com/hashtag/IoT?src=hash\"><s>#</s><b>IoT</b></a> <a class=\"twitter-hashtag pretty-link js-nav\" data-query-source=\"hashtag_click\" dir=\"ltr\" href=\"https://twitter.com/hashtag/Embedded?src=hash\"><s>#</s><b>Embedded</b></a> <a class=\"twitter-hashtag pretty-link js-nav\" data-query-source=\"hashtag_click\" dir=\"ltr\" href=\"https://twitter.com/hashtag/Debugging?src=hash\"><s>#</s><b>Debugging</b></a> <a class=\"twitter-hashtag pretty-link js-nav\" data-query-source=\"hashtag_click\" dir=\"ltr\" href=\"https://twitter.com/hashtag/UnitTesting?src=hash\"><s>#</s><b>UnitTesting</b></a> <a class=\"twitter-hashtag pretty-link js-nav\" data-query-source=\"hashtag_click\" dir=\"ltr\" href=\"https://twitter.com/hashtag/CodeAnalysis?src=hash\"><s>#</s><b>CodeAnalysis</b></a> <a class=\"twitter-hashtag pretty-link js-nav\" data-query-source=\"hashtag_click\" dir=\"ltr\" href=\"https://twitter.com/hashtag/FirmwareInspection?src=hash\"><s>#</s><b>FirmwareInspection</b></a>", "entries": {"urls": ["https://community.platformio.org/t/st-stm32-dev-platform-6-1-0/12905"], "photos": ["https://news.platformio.org/tweets/PlatformIO_Org/EU7MfeBUcAMEhAT.png"]}, "isPinned": false}, {"tweetId": "1246108302729195520", "tweetUrl": "https://twitter.com/PlatformIO_Org/status/1246108302729195520", "author": "PlatformIO", "time": 1585930345, "timeFormatted": "Apr 3", "text": "Do you follow <a class=\"twitter-hashtag pretty-link js-nav\" data-query-source=\"hashtag_click\" dir=\"ltr\" href=\"https://twitter.com/hashtag/PlatformIO?src=hash\"><s>#</s><b>PlatformIO</b></a> on LinkedIn? Click the link and connect with us today <img alt=\"\ud83e\udde1\" aria-label=\"Emoji: Orange heart\" class=\"Emoji Emoji--forText\" draggable=\"false\" src=\"https://abs.twimg.com/emoji/v2/72x72/1f9e1.png\" title=\"Orange heart\"/><br /><img alt=\"\ud83e\udd1d\" aria-label=\"Emoji: Handshake\" class=\"Emoji Emoji--forText\" draggable=\"false\" src=\"https://abs.twimg.com/emoji/v2/72x72/1f91d.png\" title=\"Handshake\"/><a class=\"twitter-timeline-link\" data-expanded-url=\"https://linkedin.com/company/platformio/\" dir=\"ltr\" href=\"https://t.co/WCxDr8PoFU\" rel=\"nofollow noopener\" target=\"_blank\" title=\"https://linkedin.com/company/platformio/\"><span class=\"tco-ellipsis\"></span><span class=\"js-display-url\">linkedin.com/company/platfo</span><span class=\"tco-ellipsis\">&hellip;</span></a><br /><img alt=\"\ud83d\udca1\" aria-label=\"Emoji: Electric light bulb\" class=\"Emoji Emoji--forText\" draggable=\"false\" src=\"https://abs.twimg.com/emoji/v2/72x72/1f4a1.png\" title=\"Electric light bulb\"/><a class=\"twitter-hashtag pretty-link js-nav\" data-query-source=\"hashtag_click\" dir=\"ltr\" href=\"https://twitter.com/hashtag/Freedom?src=hash\"><s>#</s><b>Freedom</b></a> <a class=\"twitter-hashtag pretty-link js-nav\" data-query-source=\"hashtag_click\" dir=\"ltr\" href=\"https://twitter.com/hashtag/Embedded?src=hash\"><s>#</s><b>Embedded</b></a> <a class=\"twitter-hashtag pretty-link js-nav\" data-query-source=\"hashtag_click\" dir=\"ltr\" href=\"https://twitter.com/hashtag/OpenSource?src=hash\"><s>#</s><b>OpenSource</b></a>", "entries": {"urls": ["https://linkedin.com/company/platformio/"], "photos": ["https://news.platformio.org/tweets/PlatformIO_Org/EUsQxcsXkAAa0y1.jpg"]}, "isPinned": false}, {"tweetId": "1246104835310616576", "tweetUrl": "https://twitter.com/PlatformIO_Org/status/1246104835310616576", "author": "PlatformIO", "time": 1585929518, "timeFormatted": "Apr 3", "text": "We got great feedback on <a class=\"twitter-hashtag pretty-link js-nav\" data-query-source=\"hashtag_click\" dir=\"ltr\" href=\"https://twitter.com/hashtag/Zephyr?src=hash\"><s>#</s><b>Zephyr</b></a> RTOS! This time we asked PVS-Studio Team to check its code quality <img alt=\"\ud83d\udc1b\" aria-label=\"Emoji: Bug\" class=\"Emoji Emoji--forText\" draggable=\"false\" src=\"https://abs.twimg.com/emoji/v2/72x72/1f41b.png\" title=\"Bug\"/> and compare results with <a class=\"twitter-atreply pretty-link js-nav\" data-mentioned-user-id=\"17427993\" dir=\"ltr\" href=\"https://twitter.com/synopsys\"><s>@</s><b>synopsys</b></a> Coverity SAST<br /><img alt=\"\ud83d\udc49\" aria-label=\"Emoji: Right pointing backhand index\" class=\"Emoji Emoji--forText\" draggable=\"false\" src=\"https://abs.twimg.com/emoji/v2/72x72/1f449.png\" title=\"Right pointing backhand index\"/> <a class=\"twitter-timeline-link\" data-expanded-url=\"https://www.viva64.com/en/b/0721/\" dir=\"ltr\" href=\"https://t.co/d42ASLLQAN\" rel=\"nofollow noopener\" target=\"_blank\" title=\"https://www.viva64.com/en/b/0721/\"><span class=\"tco-ellipsis\"></span><span class=\"js-display-url\">viva64.com/en/b/0721/</span><span class=\"tco-ellipsis\"></span></a><br /><img alt=\"\ud83d\udccc\" aria-label=\"Emoji: Pushpin\" class=\"Emoji Emoji--forText\" draggable=\"false\" src=\"https://abs.twimg.com/emoji/v2/72x72/1f4cc.png\" title=\"Pushpin\"/> <a class=\"twitter-hashtag pretty-link js-nav\" data-query-source=\"hashtag_click\" dir=\"ltr\" href=\"https://twitter.com/hashtag/Freedom?src=hash\"><s>#</s><b>Freedom</b></a> <a class=\"twitter-hashtag pretty-link js-nav\" data-query-source=\"hashtag_click\" dir=\"ltr\" href=\"https://twitter.com/hashtag/IDE?src=hash\"><s>#</s><b>IDE</b></a> <a class=\"twitter-hashtag pretty-link js-nav\" data-query-source=\"hashtag_click\" dir=\"ltr\" href=\"https://twitter.com/hashtag/CLI?src=hash\"><s>#</s><b>CLI</b></a> <a class=\"twitter-hashtag pretty-link js-nav\" data-query-source=\"hashtag_click\" dir=\"ltr\" href=\"https://twitter.com/hashtag/IoT?src=hash\"><s>#</s><b>IoT</b></a> <a class=\"twitter-hashtag pretty-link js-nav\" data-query-source=\"hashtag_click\" dir=\"ltr\" href=\"https://twitter.com/hashtag/Embedded?src=hash\"><s>#</s><b>Embedded</b></a> <a class=\"twitter-hashtag pretty-link js-nav\" data-query-source=\"hashtag_click\" dir=\"ltr\" href=\"https://twitter.com/hashtag/CodeAnalysis?src=hash\"><s>#</s><b>CodeAnalysis</b></a> <a class=\"twitter-hashtag pretty-link js-nav\" data-query-source=\"hashtag_click\" dir=\"ltr\" href=\"https://twitter.com/hashtag/MISRA?src=hash\"><s>#</s><b>MISRA</b></a> <a class=\"twitter-hashtag pretty-link js-nav\" data-query-source=\"hashtag_click\" dir=\"ltr\" href=\"https://twitter.com/hashtag/CWE?src=hash\"><s>#</s><b>CWE</b></a> <a class=\"twitter-hashtag pretty-link js-nav\" data-query-source=\"hashtag_click\" dir=\"ltr\" href=\"https://twitter.com/hashtag/SEI?src=hash\"><s>#</s><b>SEI</b></a> <a class=\"twitter-hashtag pretty-link js-nav\" data-query-source=\"hashtag_click\" dir=\"ltr\" href=\"https://twitter.com/hashtag/CERT?src=hash\"><s>#</s><b>CERT</b></a> <a class=\"twitter-hashtag pretty-link js-nav\" data-query-source=\"hashtag_click\" dir=\"ltr\" href=\"https://twitter.com/hashtag/OpenSource?src=hash\"><s>#</s><b>OpenSource</b></a>", "entries": {"urls": ["https://www.viva64.com/en/b/0721/"], "photos": ["https://news.platformio.org/tweets/PlatformIO_Org/EUsL_jZXQAMP_Q7.png"]}, "isPinned": false}, {"tweetId": "1245463341084151812", "tweetUrl": "https://twitter.com/PlatformIO_Org/status/1245463341084151812", "author": "PlatformIO", "time": 1585776574, "timeFormatted": "Apr 1", "text": "Great news! Full support for Zephyr Project <img alt=\"\ud83d\udca5\" aria-label=\"Emoji: Collision symbol\" class=\"Emoji Emoji--forText\" draggable=\"false\" src=\"https://abs.twimg.com/emoji/v2/72x72/1f4a5.png\" title=\"Collision symbol\"/><br />Updated Zephyr <a class=\"twitter-hashtag pretty-link js-nav\" data-query-source=\"hashtag_click\" dir=\"ltr\" href=\"https://twitter.com/hashtag/RTOS?src=hash\"><s>#</s><b>RTOS</b></a> to 2.2, native support for <a class=\"twitter-hashtag pretty-link js-nav\" data-query-source=\"hashtag_click\" dir=\"ltr\" href=\"https://twitter.com/hashtag/Lora?src=hash\"><s>#</s><b>Lora</b></a>, <a class=\"twitter-hashtag pretty-link js-nav\" data-query-source=\"hashtag_click\" dir=\"ltr\" href=\"https://twitter.com/hashtag/OpenThread?src=hash\"><s>#</s><b>OpenThread</b></a> and <a class=\"twitter-hashtag pretty-link js-nav\" data-query-source=\"hashtag_click\" dir=\"ltr\" href=\"https://twitter.com/hashtag/CANopen?src=hash\"><s>#</s><b>CANopen</b></a>, works without extra tools!<br /><img alt=\"\ud83d\udc49\" aria-label=\"Emoji: Right pointing backhand index\" class=\"Emoji Emoji--forText\" draggable=\"false\" src=\"https://abs.twimg.com/emoji/v2/72x72/1f449.png\" title=\"Right pointing backhand index\"/> <a class=\"twitter-timeline-link\" data-expanded-url=\"https://community.platformio.org/t/support-for-zephyr-2-2-0/12804\" dir=\"ltr\" href=\"https://t.co/dZpSELQDre\" rel=\"nofollow noopener\" target=\"_blank\" title=\"https://community.platformio.org/t/support-for-zephyr-2-2-0/12804\"><span class=\"tco-ellipsis\"></span><span class=\"js-display-url\">community.platformio.org/t/support-for-</span><span class=\"tco-ellipsis\">&hellip;</span></a><br /><img alt=\"\ud83d\udccc\" aria-label=\"Emoji: Pushpin\" class=\"Emoji Emoji--forText\" draggable=\"false\" src=\"https://abs.twimg.com/emoji/v2/72x72/1f4cc.png\" title=\"Pushpin\"/> <a class=\"twitter-hashtag pretty-link js-nav\" data-query-source=\"hashtag_click\" dir=\"ltr\" href=\"https://twitter.com/hashtag/Freedom?src=hash\"><s>#</s><b>Freedom</b></a> <a class=\"twitter-hashtag pretty-link js-nav\" data-query-source=\"hashtag_click\" dir=\"ltr\" href=\"https://twitter.com/hashtag/IDE?src=hash\"><s>#</s><b>IDE</b></a> <a class=\"twitter-hashtag pretty-link js-nav\" data-query-source=\"hashtag_click\" dir=\"ltr\" href=\"https://twitter.com/hashtag/CLI?src=hash\"><s>#</s><b>CLI</b></a> <a class=\"twitter-hashtag pretty-link js-nav\" data-query-source=\"hashtag_click\" dir=\"ltr\" href=\"https://twitter.com/hashtag/IoT?src=hash\"><s>#</s><b>IoT</b></a> <a class=\"twitter-hashtag pretty-link js-nav\" data-query-source=\"hashtag_click\" dir=\"ltr\" href=\"https://twitter.com/hashtag/Embedded?src=hash\"><s>#</s><b>Embedded</b></a> <a class=\"twitter-hashtag pretty-link js-nav\" data-query-source=\"hashtag_click\" dir=\"ltr\" href=\"https://twitter.com/hashtag/Debugging?src=hash\"><s>#</s><b>Debugging</b></a> <a class=\"twitter-hashtag pretty-link js-nav\" data-query-source=\"hashtag_click\" dir=\"ltr\" href=\"https://twitter.com/hashtag/UnitTesting?src=hash\"><s>#</s><b>UnitTesting</b></a> <a class=\"twitter-hashtag pretty-link js-nav\" data-query-source=\"hashtag_click\" dir=\"ltr\" href=\"https://twitter.com/hashtag/CodeAnalysis?src=hash\"><s>#</s><b>CodeAnalysis</b></a> <a class=\"twitter-hashtag pretty-link js-nav\" data-query-source=\"hashtag_click\" dir=\"ltr\" href=\"https://twitter.com/hashtag/FirmwareInspection?src=hash\"><s>#</s><b>FirmwareInspection</b></a>", "entries": {"urls": ["https://community.platformio.org/t/support-for-zephyr-2-2-0/12804"], "photos": ["https://news.platformio.org/tweets/PlatformIO_Org/EUjFjycXgAAmOv-.jpg"]}, "isPinned": false}, {"tweetId": "1244033727111598081", "tweetUrl": "https://twitter.com/Hacksterio/status/1244033727111598081", "author": "Hackster.io", "time": 1585435728, "timeFormatted": "Mar 28", "text": "How to use the <a class=\"twitter-atreply pretty-link js-nav\" data-mentioned-user-id=\"2848528606\" dir=\"ltr\" href=\"https://twitter.com/PlatformIO_Org\"><s>@</s><b>PlatformIO_Org</b></a> debugger on the ESP32 with an ESP-prog: <a class=\"twitter-timeline-link\" data-expanded-url=\"https://bit.ly/39rcqZw\" dir=\"ltr\" href=\"https://t.co/U6FCmNaC37\" rel=\"nofollow noopener\" target=\"_blank\" title=\"https://bit.ly/39rcqZw\"><span class=\"tco-ellipsis\"></span><span class=\"js-display-url\">bit.ly/39rcqZw</span><span class=\"tco-ellipsis\"></span></a>", "entries": {"urls": ["https://bit.ly/39rcqZw"], "photos": ["https://news.platformio.org/tweets/PlatformIO_Org/EUOxz1hXYAMBe3n.jpg"]}, "isPinned": false}]